ufs_tools/__init__.py
ufs_tools/app_framework.py
ufs_tools/app_tools.py
ufs_tools/basic_lib_tool.py
ufs_tools/direct_opener.py
ufs_tools/file_search.py
ufs_tools/filetools.py
ufs_tools/folder_file_distributor.py
ufs_tools/folder_file_processor.py
ufs_tools/folder_tool.py
ufs_tools/inspect_utils.py
ufs_tools/libtool.py
ufs_tools/package_info.py
ufs_tools/package_utils.py
ufs_tools/string_tools.py
ufs_tools/tuple_tools.py
ufs_tools/python_app_utils/__init__.py
ufs_tools/python_app_utils/base.py
ufs_tools/short_decorator/__init__.py
ufs_tools/short_decorator/ignore_exception.py
ufs_tools-0.5.16.dist-info/METADATA
ufs_tools-0.5.16.dist-info/RECORD
ufs_tools-0.5.16.dist-info/WHEEL
ufs_tools-0.5.16.dist-info/top_level.txt
