Metadata-Version: 2.1
Name: ufs-tools
Version: 0.5.16
Summary: Some functions can be used during python development
Home-page: https://github.com/weijia/ufs-tools
Author: Wang Richard
Author-email: richardwangwang@gmail.com
License: ISCL
Keywords: ufs_tools
Platform: UNKNOWN
Classifier: Development Status :: 2 - Pre-Alpha
Classifier: Intended Audience :: Developers
Classifier: License :: OSI Approved :: ISC License (ISCL)
Classifier: Natural Language :: English
Classifier: Programming Language :: Python :: 2
Classifier: Programming Language :: Python :: 2.6
Classifier: Programming Language :: Python :: 2.7
